la_com_request_parser/__init__.py
la_com_request_parser/com_request_parser.py
la_com_request_parser-0.2.0.dist-info/LICENSE
la_com_request_parser-0.2.0.dist-info/METADATA
la_com_request_parser-0.2.0.dist-info/WHEEL
la_com_request_parser-0.2.0.dist-info/top_level.txt
la_com_request_parser-0.2.0.dist-info/RECORD
