Metadata-Version: 2.1
Name: la-com-request-parser
Version: 0.2.0
Summary: A request parser to simplify communication with physics-lab devices
Author: Lars Neuser
Author-email: lars.coding@web.de
Classifier: Programming Language :: Python :: 3
Classifier: License :: OSI Approved :: MIT License
Classifier: Operating System :: OS Independent
Requires-Python: >=3.6
License-File: LICENSE
